wikirevparser/__init__.py
wikirevparser/wikirevparser.py
wikirevparser-0.0.8.dist-info/LICENSE
wikirevparser-0.0.8.dist-info/METADATA
wikirevparser-0.0.8.dist-info/WHEEL
wikirevparser-0.0.8.dist-info/top_level.txt
wikirevparser-0.0.8.dist-info/RECORD
