Metadata-Version: 2.1
Name: wikirevparser
Version: 0.0.8
Summary: Wikipedia revision history parser for Python
Home-page: https://github.com/ajoer/WikiRevParser
Author: Anna Jørgensen
Author-email: anka.jorgensen@gmail.com
License: MIT
Keywords: python wikipedia API
Platform: UNKNOWN
Classifier: Programming Language :: Python
Classifier: Programming Language :: Python :: 3
Classifier: License :: OSI Approved :: MIT License
Classifier: Operating System :: OS Independent
Requires-Python: >=3.6
Requires-Dist: beautifulsoup4
Requires-Dist: nltk
Requires-Dist: requests (<3.0.0,>=2.0.0)
